{
  "photo_url": "https://www.flickr.com/photos/39908901@N06/52247843840/in/pool-335743@N24/",
  "photo_id": "52247843840",
  "title": "Balanced Rock",
  "description": "Balanced Rock in Arches National Park, wide angle view in the morning light",
  "author": "m01229",
  "author_url": "https://www.flickr.com/photos/39908901@N06/",
  "tags": [],
  "views": "307views",
  "favorites": "6faves",
  "comments": "1comment",
  "date_taken": null,
  "date_uploaded": null,
  "camera_info": null,
  "geolocation": {
    "lat": 38.565374999999996,
    "lon": -109.55069722222223
  },
  "image_filename": "52247843840_Balanced_Rock.jpg",
  "generated_description": "A massive boulder perches precariously atop a narrow sandstone pedestal in a desert setting. The morning light illuminates the red rock formation against a clear blue sky. This iconic geological wonder demonstrates millions of years of wind and water erosion creating a perfectly balanced structure."
}